dev_tools/__init__.py
dev_tools/__main__.py
dev_tools/cli_utils.py
dev_tools/config.py
dev_tools/file_io.py
dev_tools/github.py
dev_tools/main.py
dev_tools/notebook.py
dev_tools/paths.py
shiba_dev_tools-0.3.0.dist-info/METADATA
shiba_dev_tools-0.3.0.dist-info/WHEEL
shiba_dev_tools-0.3.0.dist-info/entry_points.txt
shiba_dev_tools-0.3.0.dist-info/licenses/LICENSE
shiba_dev_tools-0.3.0.dist-info/RECORD
