Metadata-Version: 2.4
Name: shiba-dev-tools
Version: 0.3.0
Summary: Developer tools in a CLI
Project-URL: Homepage, https://github.com/leeaaron629/shiba-dev-tools
Project-URL: Documentation, https://github.com/leeaaron629/shiba-dev-tools#readme
Project-URL: Repository, https://github.com/leeaaron629/shiba-dev-tools
Project-URL: Issues, https://github.com/leeaaron629/shiba-dev-tools/issues
Project-URL: Changelog, https://github.com/leeaaron629/shiba-dev-tools/blob/main/CHANGELOG.md
Author-email: Aaron Lee <leeaaron629@users.noreply.github.com>
License-Expression: Apache-2.0
License-File: LICENSE
Keywords: cli,configuration,developer-tools,devtools,github,productivity
Classifier: Development Status :: 3 - Alpha
Classifier: Environment :: Console
Classifier: Intended Audience :: Developers
Classifier: License :: OSI Approved :: Apache Software License
Classifier: Operating System :: MacOS
Classifier: Operating System :: Microsoft :: Windows
Classifier: Operating System :: OS Independent
Classifier: Operating System :: POSIX :: Linux
Classifier: Programming Language :: Python :: 3
Classifier: Programming Language :: Python :: 3 :: Only
Classifier: Programming Language :: Python :: 3.10
Classifier: Programming Language :: Python :: 3.11
Classifier: Programming Language :: Python :: 3.12
Classifier: Programming Language :: Python :: 3.13
Classifier: Topic :: Software Development
Classifier: Topic :: Software Development :: Libraries :: Python Modules
Classifier: Topic :: Utilities
Classifier: Typing :: Typed
Requires-Python: >=3.10
Requires-Dist: python-dotenv==1.2.1
Requires-Dist: requests>=2.31.0
Requires-Dist: rich>=13.9.0
Requires-Dist: typer>=0.20.0
Provides-Extra: dev
Requires-Dist: pyright>=1.1.407; extra == 'dev'
Requires-Dist: pytest-cov>=4.0.0; extra == 'dev'
Requires-Dist: pytest>=9.0.1; extra == 'dev'
Requires-Dist: ruff>=0.8.6; extra == 'dev'
